{"name":"Kickstart.js","tagline":"Using a Universal Module Definition (UMD) pattern to create a library or module that offers compatibility with the most popular script loaders of the day.","body":"# Kickstart.js [![build status](https://travis-ci.org/cheton/kickstart.js.svg?branch=master)](https://travis-ci.org/cheton/kickstart.js)\r\n\r\n[![NPM](https://nodei.co/npm/kickstart-js.png?downloads=true&stars=true)](https://nodei.co/npm/kickstart-js/)\r\n\r\nUsing a Universal Module Definition (UMD) pattern to create a library or module that offers compatibility with the most popular script loaders of the day.\r\n\r\n## Supported Modules\r\n* CommonJS - [Node.js](http://nodejs.org/), [Browserify](https://github.com/substack/node-browserify), [curl.js](https://github.com/cujojs/curl) and more.\r\n* AMD - [RequireJS](https://github.com/jrburke/requirejs), [curl.js](https://github.com/cujojs/curl) and more.\r\n* Globals - Adds to window object in web browsers.\r\n","google":"","note":"Don't delete this file! It's used internally to help with page regeneration."}